setup.py
test_script.py
HelloWorld_1.egg-info/PKG-INFO
HelloWorld_1.egg-info/SOURCES.txt
HelloWorld_1.egg-info/dependency_links.txt
HelloWorld_1.egg-info/requires.txt
HelloWorld_1.egg-info/top_level.txt