Metadata-Version: 1.0
Name: HelloWorld-1
Version: 0.1
Summary: This is an Example Package
Home-page: UNKNOWN
Author: Suhanna CH
Author-email: suhanna@gmail.com
License: UNKNOWN
Keywords: hello world example examples
Platform: UNKNOWN
